Metadata-Version: 2.1
Name: spillthebeans-threejs
Version: 0.0.7
Summary: threejs component for spillthebeans landing page
Home-page: UNKNOWN
Author: Ben Cannell <bean.can.design@gmail.com>
License: GPL-3.0
Platform: UNKNOWN
Classifier: Framework :: Dash
License-File: LICENSE
